scattermind/__init__.py
scattermind/__main__.py
scattermind/py.typed
scattermind/api/__init__.py
scattermind/api/api.py
scattermind/api/loader.py
scattermind/app/__init__.py
scattermind/app/args.py
scattermind/app/healthcheck.py
scattermind/app/worker.py
scattermind/system/__init__.py
scattermind/system/base.py
scattermind/system/helper.py
scattermind/system/info.py
scattermind/system/io.py
scattermind/system/names.py
scattermind/system/plugins.py
scattermind/system/redis_util.py
scattermind/system/response.py
scattermind/system/torch_util.py
scattermind/system/util.py
scattermind/system/cache/__init__.py
scattermind/system/cache/cache.py
scattermind/system/cache/loader.py
scattermind/system/cache/nocache.py
scattermind/system/cache/redis.py
scattermind/system/client/__init__.py
scattermind/system/client/client.py
scattermind/system/client/loader.py
scattermind/system/client/local.py
scattermind/system/client/redis.py
scattermind/system/config/__init__.py
scattermind/system/config/config.py
scattermind/system/config/loader.py
scattermind/system/executor/__init__.py
scattermind/system/executor/executor.py
scattermind/system/executor/loader.py
scattermind/system/executor/redis.py
scattermind/system/executor/single.py
scattermind/system/executor/thread.py
scattermind/system/graph/__init__.py
scattermind/system/graph/args.py
scattermind/system/graph/graph.py
scattermind/system/graph/graphdef.py
scattermind/system/graph/loader.py
scattermind/system/graph/node.py
scattermind/system/graph/nodes/__init__.py
scattermind/system/graph/nodes/assertion_error.py
scattermind/system/graph/nodes/bin_op.py
scattermind/system/graph/nodes/call.py
scattermind/system/graph/nodes/constant_op.py
scattermind/system/graph/nodes/for_loop.py
scattermind/system/graph/nodes/if_op.py
scattermind/system/graph/nodes/load_constant.py
scattermind/system/graph/nodes/mat_square.py
scattermind/system/graph/nodes/str_concat.py
scattermind/system/graph/nodes/test_cache.py
scattermind-0.5.1.dist-info/LICENSE
scattermind-0.5.1.dist-info/METADATA
scattermind-0.5.1.dist-info/WHEEL
scattermind-0.5.1.dist-info/top_level.txt
scattermind-0.5.1.dist-info/RECORD
