Metadata-Version: 2.1
Name: scattermind
Version: 0.5.1
Summary: A decentralized and distributed horizontally scalable model execution framework.
Author-email: Josua Krause <josua.krause@gmail.com>
License: Apache License
Project-URL: repository, https://github.com/JosuaKrause/scattermind
Keywords: distributed,model inference,machine learning
Classifier: Development Status :: 4 - Beta
Classifier: License :: OSI Approved :: Apache Software License
Classifier: Operating System :: OS Independent
Classifier: Programming Language :: Python :: 3
Classifier: Programming Language :: Python :: 3.11
Requires-Python: >=3.11
License-File: LICENSE
Requires-Dist: mypy >=1.10.0
Requires-Dist: numpy >=1.25.2
Requires-Dist: python-dotenv >=1.0.1
Requires-Dist: quick-server >=0.10.0
Requires-Dist: redipy >=0.7.1
Requires-Dist: requests >=2.31.0
Requires-Dist: torch >=2.0.0
Provides-Extra: test
Requires-Dist: flake8-commas >=2.1.0 ; extra == 'test'
Requires-Dist: flake8-isort >=6.1.1 ; extra == 'test'
Requires-Dist: flake8 >=5.0.4 ; extra == 'test'
Requires-Dist: isort ==5.13.2 ; extra == 'test'
Requires-Dist: pre-commit >=3.4.0 ; extra == 'test'
Requires-Dist: pycodestyle >=2.9.1 ; extra == 'test'
Requires-Dist: pylint >=3.2.0 ; extra == 'test'
Requires-Dist: pytest-cov >=4.1.0 ; extra == 'test'
Requires-Dist: pytest >=7.4.2 ; extra == 'test'
Requires-Dist: types-requests >=2.31.0.2 ; extra == 'test'
